haiji_filler/__init__.py
haiji_filler/main.py
haiji_filler/src/__init__.py
haiji_filler/src/filler.py
haiji_filler-0.1.1.dist-info/METADATA
haiji_filler-0.1.1.dist-info/WHEEL
haiji_filler-0.1.1.dist-info/entry_points.txt
haiji_filler-0.1.1.dist-info/top_level.txt
haiji_filler-0.1.1.dist-info/RECORD
