Metadata-Version: 2.1
Name: haiji-filler
Version: 0.1.1
Summary: haiji filler
Home-page: UNKNOWN
Author: haiji team
License: UNKNOWN
Platform: UNKNOWN
Requires-Python: >=3.8,<4.0
